[
  {
    "product_id": 8164760322231,
    "product_title": "Lozen Jesse Top",
    "product_url": "https://midoribikinis.com/products/lozen-jesse-top",
    "image_url": "https://cdn.shopify.com/s/files/1/0230/4865/files/LozenJesseTop.jpg?v=1755408512"
  },
  {
    "product_id": 8164760322231,
    "product_title": "Lozen Jesse Top",
    "product_url": "https://midoribikinis.com/products/lozen-jesse-top",
    "image_url": "https://cdn.shopify.com/s/files/1/0230/4865/files/LozenJesseBikiniTop.jpg?v=1755408512"
  },
  {
    "product_id": 8164760322231,
    "product_title": "Lozen Jesse Top",
    "product_url": "https://midoribikinis.com/products/lozen-jesse-top",
    "image_url": "https://cdn.shopify.com/s/files/1/0230/4865/files/LozenSet_f22661e6-8cd3-4a97-9c83-62535dd2180c.png?v=1755408512"
  },
  {
    "product_id": 7893968847031,
    "product_title": "Murex Kai Bottom",
    "product_url": "https://midoribikinis.com/products/murex-kai-bottom",
    "image_url": "https://cdn.shopify.com/s/files/1/0230/4865/files/murex-kai-bottom-962886.jpg?v=1746040717"
  },
  {
    "product_id": 7893968847031,
    "product_title": "Murex Kai Bottom",
    "product_url": "https://midoribikinis.com/products/murex-kai-bottom",
    "image_url": "https://cdn.shopify.com/s/files/1/0230/4865/files/murex-kai-bottom-443961.jpg?v=1746040720"
  },
  {
    "product_id": 7829317615799,
    "product_title": "Canopy Brayden Bottom",
    "product_url": "https://midoribikinis.com/products/canopy-brayden-bottom",
    "image_url": "https://cdn.shopify.com/s/files/1/0230/4865/files/canopy-brayden-bottom-114112.jpg?v=1746041267"
  },
  {
    "product_id": 7829317615799,
    "product_title": "Canopy Brayden Bottom",
    "product_url": "https://midoribikinis.com/products/canopy-brayden-bottom",
    "image_url": "https://cdn.shopify.com/s/files/1/0230/4865/files/canopy-brayden-bottom-833641.jpg?v=1746041271"
  },
  {
    "product_id": 7784463761591,
    "product_title": "Indigo Brayden Bottom",
    "product_url": "https://midoribikinis.com/products/indigo-brayden-bottom",
    "image_url": "https://cdn.shopify.com/s/files/1/0230/4865/files/indigo-brayden-bottom-817367.jpg?v=1746041382"
  },
  {
    "product_id": 7784463761591,
    "product_title": "Indigo Brayden Bottom",
    "product_url": "https://midoribikinis.com/products/indigo-brayden-bottom",
    "image_url": "https://cdn.shopify.com/s/files/1/0230/4865/files/indigo-brayden-bottom-513922.jpg?v=1746041388"
  },
  {
    "product_id": 7561228058807,
    "product_title": "Capri Parker Bottom",
    "product_url": "https://midoribikinis.com/products/capri-parker-bottom",
    "image_url": "https://cdn.shopify.com/s/files/1/0230/4865/files/capri-parker-bottom-448325.jpg?v=1746041549"
  },
  {
    "product_id": 7561228058807,
    "product_title": "Capri Parker Bottom",
    "product_url": "https://midoribikinis.com/products/capri-parker-bottom",
    "image_url": "https://cdn.shopify.com/s/files/1/0230/4865/files/capri-parker-bottom-950861.jpg?v=1746041553"
  },
  {
    "product_id": 7561222586551,
    "product_title": "Capri Stevie Bottom",
    "product_url": "https://midoribikinis.com/products/capri-stevie-bottom",
    "image_url": "https://cdn.shopify.com/s/files/1/0230/4865/files/capri-stevie-bottom-342431.jpg?v=1746041556"
  },
  {
    "product_id": 7561222586551,
    "product_title": "Capri Stevie Bottom",
    "product_url": "https://midoribikinis.com/products/capri-stevie-bottom",
    "image_url": "https://cdn.shopify.com/s/files/1/0230/4865/files/capri-stevie-bottom-426232.jpg?v=1746041562"
  },
  {
    "product_id": 7561221111991,
    "product_title": "Capri Noah Bottom",
    "product_url": "https://midoribikinis.com/products/capri-noah-bottom",
    "image_url": "https://cdn.shopify.com/s/files/1/0230/4865/files/capri-noah-bottom-530482.jpg?v=1746041565"
  },
  {
    "product_id": 7561221111991,
    "product_title": "Capri Noah Bottom",
    "product_url": "https://midoribikinis.com/products/capri-noah-bottom",
    "image_url": "https://cdn.shopify.com/s/files/1/0230/4865/files/capri-noah-bottom-298797.jpg?v=1746041572"
  },
  {
    "product_id": 7561217376439,
    "product_title": "Capri Brayden Bottom",
    "product_url": "https://midoribikinis.com/products/capri-brayden-bottom",
    "image_url": "https://cdn.shopify.com/s/files/1/0230/4865/files/capri-brayden-bottom-570080.jpg?v=1746041576"
  },
  {
    "product_id": 7561217376439,
    "product_title": "Capri Brayden Bottom",
    "product_url": "https://midoribikinis.com/products/capri-brayden-bottom",
    "image_url": "https://cdn.shopify.com/s/files/1/0230/4865/files/capri-brayden-bottom-111893.jpg?v=1746041580"
  },
  {
    "product_id": 7400455700663,
    "product_title": "Mai Tai Zuri Bottom",
    "product_url": "https://midoribikinis.com/products/mai-tai-zuri-bottom",
    "image_url": "https://cdn.shopify.com/s/files/1/0230/4865/files/mai-tai-zuri-bottom-617393.jpg?v=1746041630"
  },
  {
    "product_id": 7400455700663,
    "product_title": "Mai Tai Zuri Bottom",
    "product_url": "https://midoribikinis.com/products/mai-tai-zuri-bottom",
    "image_url": "https://cdn.shopify.com/s/files/1/0230/4865/files/mai-tai-zuri-bottom-216482.jpg?v=1746041633"
  },
  {
    "product_id": 7345227759799,
    "product_title": "Ginger Brayden Bottom",
    "product_url": "https://midoribikinis.com/products/ginger-brayden-bottom",
    "image_url": "https://cdn.shopify.com/s/files/1/0230/4865/files/ginger-brayden-bottom-264475.jpg?v=1746041754"
  },
  {
    "product_id": 7345227759799,
    "product_title": "Ginger Brayden Bottom",
    "product_url": "https://midoribikinis.com/products/ginger-brayden-bottom",
    "image_url": "https://cdn.shopify.com/s/files/1/0230/4865/files/ginger-brayden-bottom-295099.jpg?v=1746041757"
  },
  {
    "product_id": 7893969535159,
    "product_title": "Murex Brayden Bottom",
    "product_url": "https://midoribikinis.com/products/murex-brayden-bottom",
    "image_url": "https://cdn.shopify.com/s/files/1/0230/4865/files/murex-brayden-bottom-344610.jpg?v=1746040708"
  },
  {
    "product_id": 7893969535159,
    "product_title": "Murex Brayden Bottom",
    "product_url": "https://midoribikinis.com/products/murex-brayden-bottom",
    "image_url": "https://cdn.shopify.com/s/files/1/0230/4865/files/murex-brayden-bottom-577472.jpg?v=1746040711"
  },
  {
    "product_id": 7893265907895,
    "product_title": "Pua Nora Top",
    "product_url": "https://midoribikinis.com/products/pua-nora-top",
    "image_url": "https://cdn.shopify.com/s/files/1/0230/4865/files/pua-nora-top-188840.jpg?v=1746040809"
  },
  {
    "product_id": 7893265907895,
    "product_title": "Pua Nora Top",
    "product_url": "https://midoribikinis.com/products/pua-nora-top",
    "image_url": "https://cdn.shopify.com/s/files/1/0230/4865/files/pua-nora-top-635990.jpg?v=1746040812"
  },
  {
    "product_id": 7893264793783,
    "product_title": "Pua Cruz Bottom",
    "product_url": "https://midoribikinis.com/products/pua-cruz-bottom",
    "image_url": "https://cdn.shopify.com/s/files/1/0230/4865/files/pua-cruz-bottom-305938.jpg?v=1746040829"
  },
  {
    "product_id": 7893264793783,
    "product_title": "Pua Cruz Bottom",
    "product_url": "https://midoribikinis.com/products/pua-cruz-bottom",
    "image_url": "https://cdn.shopify.com/s/files/1/0230/4865/files/pua-cruz-bottom-815340.jpg?v=1746040832"
  },
  {
    "product_id": 7893261254839,
    "product_title": "Pua Tanner Bottom",
    "product_url": "https://midoribikinis.com/products/pua-tanner-bottom",
    "image_url": "https://cdn.shopify.com/s/files/1/0230/4865/files/pua-tanner-bottom-635558.jpg?v=1746040849"
  },
  {
    "product_id": 7893261254839,
    "product_title": "Pua Tanner Bottom",
    "product_url": "https://midoribikinis.com/products/pua-tanner-bottom",
    "image_url": "https://cdn.shopify.com/s/files/1/0230/4865/files/pua-tanner-bottom-862792.jpg?v=1746040852"
  },
  {
    "product_id": 7883695718583,
    "product_title": "Pippa Tanner Bottom",
    "product_url": "https://midoribikinis.com/products/pippa-tanner-bottom",
    "image_url": "https://cdn.shopify.com/s/files/1/0230/4865/files/pippa-tanner-bottom-100459.jpg?v=1746040948"
  },
  {
    "product_id": 7883695718583,
    "product_title": "Pippa Tanner Bottom",
    "product_url": "https://midoribikinis.com/products/pippa-tanner-bottom",
    "image_url": "https://cdn.shopify.com/s/files/1/0230/4865/files/pippa-tanner-bottom-706418.jpg?v=1746040952"
  },
  {
    "product_id": 7879744684215,
    "product_title": "Laulima Noah Bottom",
    "product_url": "https://midoribikinis.com/products/laulima-noah-bottom",
    "image_url": "https://cdn.shopify.com/s/files/1/0230/4865/files/laulima-noah-bottom-710725.jpg?v=1746040989"
  },
  {
    "product_id": 7879744684215,
    "product_title": "Laulima Noah Bottom",
    "product_url": "https://midoribikinis.com/products/laulima-noah-bottom",
    "image_url": "https://cdn.shopify.com/s/files/1/0230/4865/files/laulima-noah-bottom-402511.jpg?v=1746040994"
  },
  {
    "product_id": 7872690946231,
    "product_title": "Laulima Cruz Bottom",
    "product_url": "https://midoribikinis.com/products/laulima-cruz-bottom",
    "image_url": "https://cdn.shopify.com/s/files/1/0230/4865/files/laulima-cruz-bottom-893287.jpg?v=1746041037"
  },
  {
    "product_id": 7872690946231,
    "product_title": "Laulima Cruz Bottom",
    "product_url": "https://midoribikinis.com/products/laulima-cruz-bottom",
    "image_url": "https://cdn.shopify.com/s/files/1/0230/4865/files/laulima-cruz-bottom-205369.jpg?v=1746041042"
  },
  {
    "product_id": 7872688947383,
    "product_title": "Drift Noah Bottom",
    "product_url": "https://midoribikinis.com/products/drift-noah-bottom",
    "image_url": "https://cdn.shopify.com/s/files/1/0230/4865/files/drift-noah-bottom-205237.jpg?v=1746041062"
  },
  {
    "product_id": 7872688947383,
    "product_title": "Drift Noah Bottom",
    "product_url": "https://midoribikinis.com/products/drift-noah-bottom",
    "image_url": "https://cdn.shopify.com/s/files/1/0230/4865/files/drift-noah-bottom-436270.jpg?v=1746041066"
  },
  {
    "product_id": 7864604098743,
    "product_title": "Laulima Tanner Bottom",
    "product_url": "https://midoribikinis.com/products/laulima-tanner-bottom",
    "image_url": "https://cdn.shopify.com/s/files/1/0230/4865/files/laulima-tanner-bottom-371224.jpg?v=1746041115"
  },
  {
    "product_id": 7864604098743,
    "product_title": "Laulima Tanner Bottom",
    "product_url": "https://midoribikinis.com/products/laulima-tanner-bottom",
    "image_url": "https://cdn.shopify.com/s/files/1/0230/4865/files/laulima-tanner-bottom-168762.jpg?v=1746041120"
  },
  {
    "product_id": 7864603967671,
    "product_title": "Laulima Jax Bottom",
    "product_url": "https://midoribikinis.com/products/laulima-jax-bottom",
    "image_url": "https://cdn.shopify.com/s/files/1/0230/4865/files/laulima-jax-bottom-614353.jpg?v=1746041124"
  },
  {
    "product_id": 7864603967671,
    "product_title": "Laulima Jax Bottom",
    "product_url": "https://midoribikinis.com/products/laulima-jax-bottom",
    "image_url": "https://cdn.shopify.com/s/files/1/0230/4865/files/laulima-jax-bottom-371313.jpg?v=1746041128"
  },
  {
    "product_id": 7847400112311,
    "product_title": "Verona Cruz Bottom",
    "product_url": "https://midoribikinis.com/products/verona-cruz-bottom",
    "image_url": "https://cdn.shopify.com/s/files/1/0230/4865/files/verona-cruz-bottom-335921.jpg?v=1746041148"
  },
  {
    "product_id": 7847400112311,
    "product_title": "Verona Cruz Bottom",
    "product_url": "https://midoribikinis.com/products/verona-cruz-bottom",
    "image_url": "https://cdn.shopify.com/s/files/1/0230/4865/files/verona-cruz-bottom-943992.jpg?v=1746041154"
  },
  {
    "product_id": 7838777999543,
    "product_title": "Verona Tanner Bottom",
    "product_url": "https://midoribikinis.com/products/verona-tanner-bottom",
    "image_url": "https://cdn.shopify.com/s/files/1/0230/4865/files/verona-tanner-bottom-715191.jpg?v=1746041191"
  },
  {
    "product_id": 7838777999543,
    "product_title": "Verona Tanner Bottom",
    "product_url": "https://midoribikinis.com/products/verona-tanner-bottom",
    "image_url": "https://cdn.shopify.com/s/files/1/0230/4865/files/verona-tanner-bottom-557121.jpg?v=1746041194"
  },
  {
    "product_id": 7838776885431,
    "product_title": "Verona Brayden Bottom",
    "product_url": "https://midoribikinis.com/products/verona-brayden-bottom",
    "image_url": "https://cdn.shopify.com/s/files/1/0230/4865/files/verona-brayden-bottom-106569.jpg?v=1746041198"
  },
  {
    "product_id": 7838776885431,
    "product_title": "Verona Brayden Bottom",
    "product_url": "https://midoribikinis.com/products/verona-brayden-bottom",
    "image_url": "https://cdn.shopify.com/s/files/1/0230/4865/files/verona-brayden-bottom-853539.jpg?v=1746041202"
  },
  {
    "product_id": 7829339275447,
    "product_title": "Canopy Clover Bottom",
    "product_url": "https://midoribikinis.com/products/canopy-clover-bottom",
    "image_url": "https://cdn.shopify.com/s/files/1/0230/4865/files/canopy-clover-bottom-278436.jpg?v=1746041242"
  },
  {
    "product_id": 7829339275447,
    "product_title": "Canopy Clover Bottom",
    "product_url": "https://midoribikinis.com/products/canopy-clover-bottom",
    "image_url": "https://cdn.shopify.com/s/files/1/0230/4865/files/canopy-clover-bottom-638791.jpg?v=1746041246"
  },
  {
    "product_id": 7829336850615,
    "product_title": "Canopy Noah Bottom",
    "product_url": "https://midoribikinis.com/products/canopy-noah-bottom",
    "image_url": "https://cdn.shopify.com/s/files/1/0230/4865/files/canopy-noah-bottom-615586.jpg?v=1746041250"
  },
  {
    "product_id": 7829336850615,
    "product_title": "Canopy Noah Bottom",
    "product_url": "https://midoribikinis.com/products/canopy-noah-bottom",
    "image_url": "https://cdn.shopify.com/s/files/1/0230/4865/files/canopy-noah-bottom-679193.jpg?v=1746041255"
  },
  {
    "product_id": 7794238128311,
    "product_title": "Karma Cruz Bottom",
    "product_url": "https://midoribikinis.com/products/karma-cruz-bottom",
    "image_url": "https://cdn.shopify.com/s/files/1/0230/4865/files/karma-cruz-bottom-361814.jpg?v=1746041365"
  },
  {
    "product_id": 7794238128311,
    "product_title": "Karma Cruz Bottom",
    "product_url": "https://midoribikinis.com/products/karma-cruz-bottom",
    "image_url": "https://cdn.shopify.com/s/files/1/0230/4865/files/karma-cruz-bottom-779665.jpg?v=1746041368"
  },
  {
    "product_id": 7720644313271,
    "product_title": "Marigold Tanner Bottom",
    "product_url": "https://midoribikinis.com/products/marigold-tanner-bottom",
    "image_url": "https://cdn.shopify.com/s/files/1/0230/4865/files/marigold-tanner-bottom-384299.jpg?v=1746041511"
  },
  {
    "product_id": 7720644313271,
    "product_title": "Marigold Tanner Bottom",
    "product_url": "https://midoribikinis.com/products/marigold-tanner-bottom",
    "image_url": "https://cdn.shopify.com/s/files/1/0230/4865/files/marigold-tanner-bottom-103558.jpg?v=1746041514"
  },
  {
    "product_id": 7506698174647,
    "product_title": "Maui Noah Bottom",
    "product_url": "https://midoribikinis.com/products/maui-noah-bottom",
    "image_url": "https://cdn.shopify.com/s/files/1/0230/4865/files/maui-noah-bottom-876978.jpg?v=1746041590"
  },
  {
    "product_id": 7506698174647,
    "product_title": "Maui Noah Bottom",
    "product_url": "https://midoribikinis.com/products/maui-noah-bottom",
    "image_url": "https://cdn.shopify.com/s/files/1/0230/4865/files/maui-noah-bottom-663282.jpg?v=1746041597"
  },
  {
    "product_id": 7437662388407,
    "product_title": "Ocean Stevie Bottom",
    "product_url": "https://midoribikinis.com/products/ocean-stevie-bottom",
    "image_url": "https://cdn.shopify.com/s/files/1/0230/4865/files/ocean-stevie-bottom-339132.jpg?v=1746041608"
  },
  {
    "product_id": 7437662388407,
    "product_title": "Ocean Stevie Bottom",
    "product_url": "https://midoribikinis.com/products/ocean-stevie-bottom",
    "image_url": "https://cdn.shopify.com/s/files/1/0230/4865/files/ocean-stevie-bottom-588494.jpg?v=1746041612"
  },
  {
    "product_id": 7361764819127,
    "product_title": "Rezzy Zuri Bottom",
    "product_url": "https://midoribikinis.com/products/rezzy-zuri-bottom",
    "image_url": "https://cdn.shopify.com/s/files/1/0230/4865/files/rezzy-zuri-bottom-534875.jpg?v=1746041678"
  },
  {
    "product_id": 7361764819127,
    "product_title": "Rezzy Zuri Bottom",
    "product_url": "https://midoribikinis.com/products/rezzy-zuri-bottom",
    "image_url": "https://cdn.shopify.com/s/files/1/0230/4865/files/rezzy-zuri-bottom-131183.jpg?v=1746041681"
  },
  {
    "product_id": 7361764786359,
    "product_title": "Rezzy Jolie Bottom",
    "product_url": "https://midoribikinis.com/products/rezzy-jolie-bottom",
    "image_url": "https://cdn.shopify.com/s/files/1/0230/4865/files/rezzy-jolie-bottom-196286.jpg?v=1746041685"
  },
  {
    "product_id": 7361764786359,
    "product_title": "Rezzy Jolie Bottom",
    "product_url": "https://midoribikinis.com/products/rezzy-jolie-bottom",
    "image_url": "https://cdn.shopify.com/s/files/1/0230/4865/files/rezzy-jolie-bottom-556073.jpg?v=1746041689"
  },
  {
    "product_id": 7345227890871,
    "product_title": "Ginger Jolie Bottom",
    "product_url": "https://midoribikinis.com/products/ginger-jolie-bottom",
    "image_url": "https://cdn.shopify.com/s/files/1/0230/4865/files/ginger-jolie-bottom-724295.jpg?v=1746041746"
  },
  {
    "product_id": 7345227890871,
    "product_title": "Ginger Jolie Bottom",
    "product_url": "https://midoribikinis.com/products/ginger-jolie-bottom",
    "image_url": "https://cdn.shopify.com/s/files/1/0230/4865/files/ginger-jolie-bottom-431423.jpg?v=1746041750"
  },
  {
    "product_id": 7318078881975,
    "product_title": "Aruba Kai Bottom",
    "product_url": "https://midoribikinis.com/products/aruba-kai-bottom",
    "image_url": "https://cdn.shopify.com/s/files/1/0230/4865/files/aruba-kai-bottom-299023.jpg?v=1746041771"
  },
  {
    "product_id": 7318078881975,
    "product_title": "Aruba Kai Bottom",
    "product_url": "https://midoribikinis.com/products/aruba-kai-bottom",
    "image_url": "https://cdn.shopify.com/s/files/1/0230/4865/files/aruba-kai-bottom-730683.jpg?v=1746041776"
  },
  {
    "product_id": 7313464066231,
    "product_title": "White Kai Bottom",
    "product_url": "https://midoribikinis.com/products/white-kai-bottom",
    "image_url": "https://cdn.shopify.com/s/files/1/0230/4865/files/white-kai-bottom-930594.jpg?v=1746041803"
  },
  {
    "product_id": 7313464066231,
    "product_title": "White Kai Bottom",
    "product_url": "https://midoribikinis.com/products/white-kai-bottom",
    "image_url": "https://cdn.shopify.com/s/files/1/0230/4865/files/white-kai-bottom-512624.jpg?v=1718202822"
  },
  {
    "product_id": 7935188664503,
    "product_title": "Malta Clover Bottom",
    "product_url": "https://midoribikinis.com/products/malta-clover-bottom",
    "image_url": "https://cdn.shopify.com/s/files/1/0230/4865/files/malta-clover-bottommidori-bikinis-513565.png?v=1746040590"
  },
  {
    "product_id": 7935188664503,
    "product_title": "Malta Clover Bottom",
    "product_url": "https://midoribikinis.com/products/malta-clover-bottom",
    "image_url": "https://cdn.shopify.com/s/files/1/0230/4865/files/malta-clover-bottommidori-bikinis-155580.png?v=1746040594"
  },
  {
    "product_id": 7935180079287,
    "product_title": "Malta Brayden Bottom",
    "product_url": "https://midoribikinis.com/products/malta-brayden-bottom",
    "image_url": "https://cdn.shopify.com/s/files/1/0230/4865/files/malta-whale-tale-bottommidori-bikinis-792196.png?v=1746040617"
  },
  {
    "product_id": 7935180079287,
    "product_title": "Malta Brayden Bottom",
    "product_url": "https://midoribikinis.com/products/malta-brayden-bottom",
    "image_url": "https://cdn.shopify.com/s/files/1/0230/4865/files/malta-brayden-bottommidori-bikinis-106325.png?v=1746040623"
  },
  {
    "product_id": 7872689766583,
    "product_title": "Verona Noah Bottom",
    "product_url": "https://midoribikinis.com/products/verona-noah-bottom",
    "image_url": "https://cdn.shopify.com/s/files/1/0230/4865/files/verona-noah-bottom-904154.jpg?v=1746041052"
  },
  {
    "product_id": 7872689766583,
    "product_title": "Verona Noah Bottom",
    "product_url": "https://midoribikinis.com/products/verona-noah-bottom",
    "image_url": "https://cdn.shopify.com/s/files/1/0230/4865/files/verona-noah-bottom-930969.jpg?v=1746041058"
  },
  {
    "product_id": 7838784749751,
    "product_title": "Canopy Stevie Bottom",
    "product_url": "https://midoribikinis.com/products/canopy-stevie-bottom",
    "image_url": "https://cdn.shopify.com/s/files/1/0230/4865/files/canopy-stevie-bottom-178802.jpg?v=1746041159"
  },
  {
    "product_id": 7838784749751,
    "product_title": "Canopy Stevie Bottom",
    "product_url": "https://midoribikinis.com/products/canopy-stevie-bottom",
    "image_url": "https://cdn.shopify.com/s/files/1/0230/4865/files/canopy-stevie-bottom-246309.jpg?v=1746041163"
  },
  {
    "product_id": 7829223702711,
    "product_title": "Aloe Selah Top",
    "product_url": "https://midoribikinis.com/products/aloe-selah-top",
    "image_url": "https://cdn.shopify.com/s/files/1/0230/4865/files/aloe-selah-top-446820.jpg?v=1746041325"
  },
  {
    "product_id": 7829223702711,
    "product_title": "Aloe Selah Top",
    "product_url": "https://midoribikinis.com/products/aloe-selah-top",
    "image_url": "https://cdn.shopify.com/s/files/1/0230/4865/files/aloe-selah-top-669781.jpg?v=1746041329"
  },
  {
    "product_id": 7792137568439,
    "product_title": "Peachy Stevie Bottom",
    "product_url": "https://midoribikinis.com/products/peachy-stevie-bottom",
    "image_url": "https://cdn.shopify.com/s/files/1/0230/4865/files/peachy-stevie-bottom-549912.jpg?v=1722352245"
  },
  {
    "product_id": 7792137568439,
    "product_title": "Peachy Stevie Bottom",
    "product_url": "https://midoribikinis.com/products/peachy-stevie-bottom",
    "image_url": "https://cdn.shopify.com/s/files/1/0230/4865/files/peachy-stevie-bottom-457227.jpg?v=1746041375"
  },
  {
    "product_id": 7792137568439,
    "product_title": "Peachy Stevie Bottom",
    "product_url": "https://midoribikinis.com/products/peachy-stevie-bottom",
    "image_url": "https://cdn.shopify.com/s/files/1/0230/4865/files/peachy-stevie-bottom-921130.jpg?v=1746041378"
  },
  {
    "product_id": 7358905483447,
    "product_title": "Nala Jolie Bottom",
    "product_url": "https://midoribikinis.com/products/nala-jolie-bottom",
    "image_url": "https://cdn.shopify.com/s/files/1/0230/4865/files/nala-jolie-bottom-743388.jpg?v=1746041693"
  },
  {
    "product_id": 7358905483447,
    "product_title": "Nala Jolie Bottom",
    "product_url": "https://midoribikinis.com/products/nala-jolie-bottom",
    "image_url": "https://cdn.shopify.com/s/files/1/0230/4865/files/nala-jolie-bottom-596728.jpg?v=1746041697"
  },
  {
    "product_id": 7357392650423,
    "product_title": "Bungalow Jolie Bottom",
    "product_url": "https://midoribikinis.com/products/bungalow-jolie-bottom",
    "image_url": "https://cdn.shopify.com/s/files/1/0230/4865/files/bungalow-jolie-bottom-460064.jpg?v=1746041708"
  },
  {
    "product_id": 7357392650423,
    "product_title": "Bungalow Jolie Bottom",
    "product_url": "https://midoribikinis.com/products/bungalow-jolie-bottom",
    "image_url": "https://cdn.shopify.com/s/files/1/0230/4865/files/bungalow-jolie-bottom-539609.jpg?v=1746041712"
  },
  {
    "product_id": 7437662355639,
    "product_title": "Irie Becca Top",
    "product_url": "https://midoribikinis.com/products/irie-becca-top",
    "image_url": "https://cdn.shopify.com/s/files/1/0230/4865/files/irie-becca-top-452118.jpg?v=1718202779"
  },
  {
    "product_id": 7437662355639,
    "product_title": "Irie Becca Top",
    "product_url": "https://midoribikinis.com/products/irie-becca-top",
    "image_url": "https://cdn.shopify.com/s/files/1/0230/4865/files/irie-becca-top-879027.jpg?v=1718202779"
  },
  {
    "product_id": 8164987863223,
    "product_title": "Byron Jesse Top",
    "product_url": "https://midoribikinis.com/products/byron-jesse-top",
    "image_url": "https://cdn.shopify.com/s/files/1/0230/4865/files/ByronJesseTop_c36415fb-730b-445c-bafe-f39a9a31d73a_1.jpg?v=1757050805"
  },
  {
    "product_id": 8164987863223,
    "product_title": "Byron Jesse Top",
    "product_url": "https://midoribikinis.com/products/byron-jesse-top",
    "image_url": "https://cdn.shopify.com/s/files/1/0230/4865/files/ByronJesseBikiniTop_d40ab790-a6eb-4de3-9d3c-df612badb024_1.jpg?v=1757050805"
  },
  {
    "product_id": 8164987863223,
    "product_title": "Byron Jesse Top",
    "product_url": "https://midoribikinis.com/products/byron-jesse-top",
    "image_url": "https://cdn.shopify.com/s/files/1/0230/4865/files/Byron_Jesse_Top_and_Kai_Bottom.png?v=1757050805"
  },
  {
    "product_id": 8164987863223,
    "product_title": "Byron Jesse Top",
    "product_url": "https://midoribikinis.com/products/byron-jesse-top",
    "image_url": "https://cdn.shopify.com/s/files/1/0230/4865/files/Byron_Jesse_Bikini_Top.png?v=1757050805"
  },
  {
    "product_id": 8164987863223,
    "product_title": "Byron Jesse Top",
    "product_url": "https://midoribikinis.com/products/byron-jesse-top",
    "image_url": "https://cdn.shopify.com/s/files/1/0230/4865/files/ByronSet.png?v=1757050805"
  },
  {
    "product_id": 8164985962679,
    "product_title": "Byron Kai Bottom",
    "product_url": "https://midoribikinis.com/products/byron-kai-bottom",
    "image_url": "https://cdn.shopify.com/s/files/1/0230/4865/files/ByronKaiBottom_25ae507c-2bf4-4097-9774-a1de8553c8a3_1.jpg?v=1757050726"
  },
  {
    "product_id": 8164985962679,
    "product_title": "Byron Kai Bottom",
    "product_url": "https://midoribikinis.com/products/byron-kai-bottom",
    "image_url": "https://cdn.shopify.com/s/files/1/0230/4865/files/ByronKaiBikiniBottom_0ac9d395-b68e-4160-af81-e39d5e8b605c_1.jpg?v=1757050726"
  },
  {
    "product_id": 8164983308471,
    "product_title": "Alani Kai Bottom",
    "product_url": "https://midoribikinis.com/products/alani-kai-bottom",
    "image_url": "https://cdn.shopify.com/s/files/1/0230/4865/files/AlaniKaiBottom_fe571e4f-6be1-4b9a-aa2d-25eca077fce8.jpg?v=1755408539"
  },
  {
    "product_id": 8164983308471,
    "product_title": "Alani Kai Bottom",
    "product_url": "https://midoribikinis.com/products/alani-kai-bottom",
    "image_url": "https://cdn.shopify.com/s/files/1/0230/4865/files/AlaniKaiBikiniBottom_687df795-f0a3-4dc9-aee8-8ba9a9e39dd2.jpg?v=1755408539"
  },
  {
    "product_id": 8164982653111,
    "product_title": "Alani Jesse Top",
    "product_url": "https://midoribikinis.com/products/alani-jesse-top",
    "image_url": "https://cdn.shopify.com/s/files/1/0230/4865/files/AlaniJesseTop.jpg?v=1755408559"
  },
  {
    "product_id": 8164982653111,
    "product_title": "Alani Jesse Top",
    "product_url": "https://midoribikinis.com/products/alani-jesse-top",
    "image_url": "https://cdn.shopify.com/s/files/1/0230/4865/files/AlaniJesseBikiniTop.jpg?v=1755408559"
  },
  {
    "product_id": 8164981932215,
    "product_title": "Cobain Jesse Top",
    "product_url": "https://midoribikinis.com/products/cobain-jesse-top",
    "image_url": "https://cdn.shopify.com/s/files/1/0230/4865/files/CobainJesseBikiniTop.jpg?v=1755478501"
  },
  {
    "product_id": 8164981932215,
    "product_title": "Cobain Jesse Top",
    "product_url": "https://midoribikinis.com/products/cobain-jesse-top",
    "image_url": "https://cdn.shopify.com/s/files/1/0230/4865/files/CobainJesseTop.jpg?v=1755478501"
  },
  {
    "product_id": 8164981080247,
    "product_title": "Cobain Kai Bottom",
    "product_url": "https://midoribikinis.com/products/cobain-kai-bottom",
    "image_url": "https://cdn.shopify.com/s/files/1/0230/4865/files/CobainKaiBottom.jpg?v=1755478562"
  },
  {
    "product_id": 8164981080247,
    "product_title": "Cobain Kai Bottom",
    "product_url": "https://midoribikinis.com/products/cobain-kai-bottom",
    "image_url": "https://cdn.shopify.com/s/files/1/0230/4865/files/CobainKaiBikiniBottom.jpg?v=1755478562"
  },
  {
    "product_id": 8164979212471,
    "product_title": "Hibiscus Honey Jesse Top",
    "product_url": "https://midoribikinis.com/products/hibiscus-honey-jesse-top",
    "image_url": "https://cdn.shopify.com/s/files/1/0230/4865/files/HibiscusJesseTop.jpg?v=1755018274"
  },
  {
    "product_id": 8164979212471,
    "product_title": "Hibiscus Honey Jesse Top",
    "product_url": "https://midoribikinis.com/products/hibiscus-honey-jesse-top",
    "image_url": "https://cdn.shopify.com/s/files/1/0230/4865/files/HibiscusJesseTop_8cb9ca42-1702-4734-b252-340829a720be.jpg?v=1755018274"
  },
  {
    "product_id": 8164979212471,
    "product_title": "Hibiscus Honey Jesse Top",
    "product_url": "https://midoribikinis.com/products/hibiscus-honey-jesse-top",
    "image_url": "https://cdn.shopify.com/s/files/1/0230/4865/files/JesseTopHibiscusHoney.png?v=1755018274"
  },
  {
    "product_id": 8164978688183,
    "product_title": "Hibiscus Honey Kai Bottom",
    "product_url": "https://midoribikinis.com/products/hibiscus-honey-kai-bottom",
    "image_url": "https://cdn.shopify.com/s/files/1/0230/4865/files/HibiscusKaiBottom.jpg?v=1755018310"
  },
  {
    "product_id": 8164978688183,
    "product_title": "Hibiscus Honey Kai Bottom",
    "product_url": "https://midoribikinis.com/products/hibiscus-honey-kai-bottom",
    "image_url": "https://cdn.shopify.com/s/files/1/0230/4865/files/HibiscusKaiBikiniBottom.jpg?v=1755018310"
  },
  {
    "product_id": 8164978688183,
    "product_title": "Hibiscus Honey Kai Bottom",
    "product_url": "https://midoribikinis.com/products/hibiscus-honey-kai-bottom",
    "image_url": "https://cdn.shopify.com/s/files/1/0230/4865/files/JesseTopHibiscusHoney_0fdcea61-d387-4684-bd6b-425bbd5ea68e.png?v=1755018310"
  },
  {
    "product_id": 8164971806903,
    "product_title": "Lozen Kai Bottom",
    "product_url": "https://midoribikinis.com/products/lozen-kai-bottom",
    "image_url": "https://cdn.shopify.com/s/files/1/0230/4865/files/LozenKaiBottom_d9ef2087-b2a2-491b-858f-25d5452742da.jpg?v=1755408494"
  },
  {
    "product_id": 8164971806903,
    "product_title": "Lozen Kai Bottom",
    "product_url": "https://midoribikinis.com/products/lozen-kai-bottom",
    "image_url": "https://cdn.shopify.com/s/files/1/0230/4865/files/LozenKaiBikinniBottom.jpg?v=1755408494"
  },
  {
    "product_id": 7974014451895,
    "product_title": "Tide Noah Bottom",
    "product_url": "https://midoribikinis.com/products/tide-noah-bottom-1",
    "image_url": "https://cdn.shopify.com/s/files/1/0230/4865/files/tide-noah-bottommidori-bikinis-681655.jpg?v=1746040446"
  },
  {
    "product_id": 7974014451895,
    "product_title": "Tide Noah Bottom",
    "product_url": "https://midoribikinis.com/products/tide-noah-bottom-1",
    "image_url": "https://cdn.shopify.com/s/files/1/0230/4865/files/tide-noah-bottommidori-bikinis-616302.jpg?v=1746040451"
  },
  {
    "product_id": 7974005080247,
    "product_title": "Tide Kai Bottom",
    "product_url": "https://midoribikinis.com/products/tide-kai-bottom",
    "image_url": "https://cdn.shopify.com/s/files/1/0230/4865/files/tide-kai-bottommidori-bikinis-318995.jpg?v=1746040488"
  },
  {
    "product_id": 7974005080247,
    "product_title": "Tide Kai Bottom",
    "product_url": "https://midoribikinis.com/products/tide-kai-bottom",
    "image_url": "https://cdn.shopify.com/s/files/1/0230/4865/files/tide-kai-bottommidori-bikinis-515979.jpg?v=1746040491"
  },
  {
    "product_id": 7998176624823,
    "product_title": "Mystery Bikini Bottom",
    "product_url": "https://midoribikinis.com/products/mystery-bikini-bottom",
    "image_url": "https://cdn.shopify.com/s/files/1/0230/4865/files/31.png?v=1753806326"
  },
  {
    "product_id": 8104802189495,
    "product_title": "Lozen Men's Boardshorts",
    "product_url": "https://midoribikinis.com/products/lozen-mens-boardshorts",
    "image_url": "https://cdn.shopify.com/s/files/1/0230/4865/files/LozenMen_sShorts.jpg?v=1755476234"
  },
  {
    "product_id": 8104802189495,
    "product_title": "Lozen Men's Boardshorts",
    "product_url": "https://midoribikinis.com/products/lozen-mens-boardshorts",
    "image_url": "https://cdn.shopify.com/s/files/1/0230/4865/files/LozenMen_sBoardshorts.jpg?v=1755476234"
  },
  {
    "product_id": 8104802189495,
    "product_title": "Lozen Men's Boardshorts",
    "product_url": "https://midoribikinis.com/products/lozen-mens-boardshorts",
    "image_url": "https://cdn.shopify.com/s/files/1/0230/4865/files/LozenMen_sBoardshorts.png?v=1755476234"
  },
  {
    "product_id": 8104802189495,
    "product_title": "Lozen Men's Boardshorts",
    "product_url": "https://midoribikinis.com/products/lozen-mens-boardshorts",
    "image_url": "https://cdn.shopify.com/s/files/1/0230/4865/files/LozenMen_s.png?v=1755476234"
  },
  {
    "product_id": 8104802189495,
    "product_title": "Lozen Men's Boardshorts",
    "product_url": "https://midoribikinis.com/products/lozen-mens-boardshorts",
    "image_url": "https://cdn.shopify.com/s/files/1/0230/4865/files/LozenMatchingSwim.png?v=1755476234"
  },
  {
    "product_id": 8104802189495,
    "product_title": "Lozen Men's Boardshorts",
    "product_url": "https://midoribikinis.com/products/lozen-mens-boardshorts",
    "image_url": "https://cdn.shopify.com/s/files/1/0230/4865/files/LozenBeachBoardshorts.png?v=1755476234"
  },
  {
    "product_id": 8104802189495,
    "product_title": "Lozen Men's Boardshorts",
    "product_url": "https://midoribikinis.com/products/lozen-mens-boardshorts",
    "image_url": "https://cdn.shopify.com/s/files/1/0230/4865/files/LozenBoardshorts.png?v=1755476234"
  },
  {
    "product_id": 7720643461303,
    "product_title": "Marigold Jax Bottom",
    "product_url": "https://midoribikinis.com/products/marigold-jax-bottom",
    "image_url": "https://cdn.shopify.com/s/files/1/0230/4865/files/marigold-jax-bottom-538686.jpg?v=1746041517"
  },
  {
    "product_id": 7720643461303,
    "product_title": "Marigold Jax Bottom",
    "product_url": "https://midoribikinis.com/products/marigold-jax-bottom",
    "image_url": "https://cdn.shopify.com/s/files/1/0230/4865/files/marigold-jax-bottom-413296.jpg?v=1746041520"
  },
  {
    "product_id": 8105680502967,
    "product_title": "Laylow Boy's Classic Swim Trunk",
    "product_url": "https://midoribikinis.com/products/laylow-boys-classic-swim-trunk",
    "image_url": "https://cdn.shopify.com/s/files/1/0230/4865/files/Boy_sLaylowBoardshorts.jpg?v=1746501853"
  },
  {
    "product_id": 8105680502967,
    "product_title": "Laylow Boy's Classic Swim Trunk",
    "product_url": "https://midoribikinis.com/products/laylow-boys-classic-swim-trunk",
    "image_url": "https://cdn.shopify.com/s/files/1/0230/4865/files/Boy_sLaylowBoardshortsBack.jpg?v=1746501853"
  },
  {
    "product_id": 8104828764343,
    "product_title": "Laylow Men's Classic Swim Trunk",
    "product_url": "https://midoribikinis.com/products/laylow-mens-classic-swim-trunk",
    "image_url": "https://cdn.shopify.com/s/files/1/0230/4865/files/Men_sLaylowBoardshorts.jpg?v=1746501742"
  },
  {
    "product_id": 8104828764343,
    "product_title": "Laylow Men's Classic Swim Trunk",
    "product_url": "https://midoribikinis.com/products/laylow-mens-classic-swim-trunk",
    "image_url": "https://cdn.shopify.com/s/files/1/0230/4865/files/Men_sLaylowBoardshortsBack.jpg?v=1746501742"
  },
  {
    "product_id": 8031626690743,
    "product_title": "Talise Kinsley Top",
    "product_url": "https://midoribikinis.com/products/talise-kinsley-top",
    "image_url": "https://cdn.shopify.com/s/files/1/0230/4865/files/Talise-Blue-Kinsley-Top-Womens-Slip-On-Yoga-and-Swim-Top-Midori-Bikinis.png?v=1746059802"
  },
  {
    "product_id": 8031626690743,
    "product_title": "Talise Kinsley Top",
    "product_url": "https://midoribikinis.com/products/talise-kinsley-top",
    "image_url": "https://cdn.shopify.com/s/files/1/0230/4865/files/Talise-Blue-Kinsley-Top-Womens-Slip-On-Yoga-and-Swim-Top-Midori-Bikinis_1.png?v=1746059802"
  },
  {
    "product_id": 8031626690743,
    "product_title": "Talise Kinsley Top",
    "product_url": "https://midoribikinis.com/products/talise-kinsley-top",
    "image_url": "https://cdn.shopify.com/s/files/1/0230/4865/files/Talise-Blue-Kinsley-Top-Womens-Slip-On-Yoga-and-Swim-Top-Midori-Bikinis_2.png?v=1746059802"
  },
  {
    "product_id": 8031626690743,
    "product_title": "Talise Kinsley Top",
    "product_url": "https://midoribikinis.com/products/talise-kinsley-top",
    "image_url": "https://cdn.shopify.com/s/files/1/0230/4865/files/Talise-Blue-Kinsley-Top-Womens-Slip-On-Yoga-and-Swim-Top-Midori-Bikinis_3.png?v=1746059802"
  },
  {
    "product_id": 8031621841079,
    "product_title": "Zoya Kinsley Top",
    "product_url": "https://midoribikinis.com/products/zoya-kinsley-top",
    "image_url": "https://cdn.shopify.com/s/files/1/0230/4865/files/Zoya-Orange-Kinsley-Top-Womens-Slip-On-Yoga-and-Swim-Top-Midori-Bikinis.png?v=1746059820"
  },
  {
    "product_id": 8031621841079,
    "product_title": "Zoya Kinsley Top",
    "product_url": "https://midoribikinis.com/products/zoya-kinsley-top",
    "image_url": "https://cdn.shopify.com/s/files/1/0230/4865/files/Zoya-Orange-Kinsley-Top-Womens-Slip-On-Yoga-and-Swim-Top-Midori-Bikinis_1.png?v=1746059820"
  },
  {
    "product_id": 8031621841079,
    "product_title": "Zoya Kinsley Top",
    "product_url": "https://midoribikinis.com/products/zoya-kinsley-top",
    "image_url": "https://cdn.shopify.com/s/files/1/0230/4865/files/Zoya-Orange-Kinsley-Top-Womens-Slip-On-Yoga-and-Swim-Top-Midori-Bikinis_2.png?v=1746059820"
  },
  {
    "product_id": 8031621841079,
    "product_title": "Zoya Kinsley Top",
    "product_url": "https://midoribikinis.com/products/zoya-kinsley-top",
    "image_url": "https://cdn.shopify.com/s/files/1/0230/4865/files/Zoya-Orange-Kinsley-Top-Womens-Slip-On-Yoga-and-Swim-Top-Midori-Bikinis_3.png?v=1746059820"
  },
  {
    "product_id": 8031619973303,
    "product_title": "Zoya Clover Bottom",
    "product_url": "https://midoribikinis.com/products/zoya-clover-bottom",
    "image_url": "https://cdn.shopify.com/s/files/1/0230/4865/files/Zoya-Orange-Clover-Bikini-Tie-Side-Skimpy-Clover-Swimwear-Bottom-Midori-Bikinis.png?v=1746059827"
  },
  {
    "product_id": 8031619973303,
    "product_title": "Zoya Clover Bottom",
    "product_url": "https://midoribikinis.com/products/zoya-clover-bottom",
    "image_url": "https://cdn.shopify.com/s/files/1/0230/4865/files/Zoya-Orange-Clover-Bikini-Tie-Side-Skimpy-Clover-Swimwear-Bottom-Midori-Bikinis_1.png?v=1746059827"
  },
  {
    "product_id": 8031619973303,
    "product_title": "Zoya Clover Bottom",
    "product_url": "https://midoribikinis.com/products/zoya-clover-bottom",
    "image_url": "https://cdn.shopify.com/s/files/1/0230/4865/files/Zoya-Orange-Clover-Bikini-Tie-Side-Skimpy-Clover-Swimwear-Bottom-Midori-Bikinis_2.png?v=1746059827"
  },
  {
    "product_id": 8031619121335,
    "product_title": "Zoya Kai Bottom",
    "product_url": "https://midoribikinis.com/products/zoya-kai-bottom",
    "image_url": "https://cdn.shopify.com/s/files/1/0230/4865/files/Zoya-Orange-Kai-Skimpy-Bikini-Bottom-Midori-Bikinis-Midori-Bikinis.png?v=1746059831"
  },
  {
    "product_id": 8031619121335,
    "product_title": "Zoya Kai Bottom",
    "product_url": "https://midoribikinis.com/products/zoya-kai-bottom",
    "image_url": "https://cdn.shopify.com/s/files/1/0230/4865/files/Zoya-Orange-Kai-Skimpy-Bikini-Bottom-Midori-Bikinis-Midori-Bikinis_1.png?v=1746059831"
  },
  {
    "product_id": 7974011109559,
    "product_title": "Tide Whale Tale Bottom",
    "product_url": "https://midoribikinis.com/products/tide-whale-tale-bottom",
    "image_url": "https://cdn.shopify.com/s/files/1/0230/4865/files/tide-whale-tale-bottommidori-bikinis-326886.jpg?v=1746040455"
  },
  {
    "product_id": 7974011109559,
    "product_title": "Tide Whale Tale Bottom",
    "product_url": "https://midoribikinis.com/products/tide-whale-tale-bottom",
    "image_url": "https://cdn.shopify.com/s/files/1/0230/4865/files/tide-whale-tale-bottommidori-bikinis-609502.jpg?v=1746040459"
  },
  {
    "product_id": 7935204786359,
    "product_title": "Malta Hana Top",
    "product_url": "https://midoribikinis.com/products/malta-hana-top",
    "image_url": "https://cdn.shopify.com/s/files/1/0230/4865/files/malta-hana-topmidori-bikinis-907061.png?v=1746040534"
  },
  {
    "product_id": 7935204786359,
    "product_title": "Malta Hana Top",
    "product_url": "https://midoribikinis.com/products/malta-hana-top",
    "image_url": "https://cdn.shopify.com/s/files/1/0230/4865/files/malta-hana-topmidori-bikinis-161332.png?v=1746040537"
  },
  {
    "product_id": 7935176147127,
    "product_title": "Malta Cruz Bottom",
    "product_url": "https://midoribikinis.com/products/malta-cruz-bottom",
    "image_url": "https://cdn.shopify.com/s/files/1/0230/4865/files/malta-cruz-bottommidori-bikinis-805388.png?v=1746040634"
  },
  {
    "product_id": 7935176147127,
    "product_title": "Malta Cruz Bottom",
    "product_url": "https://midoribikinis.com/products/malta-cruz-bottom",
    "image_url": "https://cdn.shopify.com/s/files/1/0230/4865/files/malta-cruz-bottommidori-bikinis-430802.png?v=1746040637"
  },
  {
    "product_id": 7914216423607,
    "product_title": "Nelly Jesse Top",
    "product_url": "https://midoribikinis.com/products/nelly-jesse-top",
    "image_url": "https://cdn.shopify.com/s/files/1/0230/4865/files/NellyJesseTop.png?v=1746040642"
  },
  {
    "product_id": 7914216423607,
    "product_title": "Nelly Jesse Top",
    "product_url": "https://midoribikinis.com/products/nelly-jesse-top",
    "image_url": "https://cdn.shopify.com/s/files/1/0230/4865/files/NellyJesseBikiniTop.png?v=1746040647"
  },
  {
    "product_id": 7914216161463,
    "product_title": "Nelly Kai Bottom",
    "product_url": "https://midoribikinis.com/products/nelly-kai-bottom",
    "image_url": "https://cdn.shopify.com/s/files/1/0230/4865/files/nelly-kai-bottom-684986.png?v=1746040651"
  },
  {
    "product_id": 7914216161463,
    "product_title": "Nelly Kai Bottom",
    "product_url": "https://midoribikinis.com/products/nelly-kai-bottom",
    "image_url": "https://cdn.shopify.com/s/files/1/0230/4865/files/nelly-kai-bottom-593053.png?v=1746040655"
  },
  {
    "product_id": 7914214391991,
    "product_title": "Nelly Brayden Bottom",
    "product_url": "https://midoribikinis.com/products/nelly-brayden-bottom",
    "image_url": "https://cdn.shopify.com/s/files/1/0230/4865/files/nelly-brayden-bottom-159033.png?v=1746040688"
  },
  {
    "product_id": 7914214391991,
    "product_title": "Nelly Brayden Bottom",
    "product_url": "https://midoribikinis.com/products/nelly-brayden-bottom",
    "image_url": "https://cdn.shopify.com/s/files/1/0230/4865/files/nelly-brayden-bottom-224683.png?v=1746040691"
  },
  {
    "product_id": 7368234598583,
    "product_title": "Ecru Brayden Bottom",
    "product_url": "https://midoribikinis.com/products/ecru-brayden-bottom",
    "image_url": "https://cdn.shopify.com/s/files/1/0230/4865/files/ecru-brayden-bottom-145026.jpg?v=1746041650"
  },
  {
    "product_id": 7368234598583,
    "product_title": "Ecru Brayden Bottom",
    "product_url": "https://midoribikinis.com/products/ecru-brayden-bottom",
    "image_url": "https://cdn.shopify.com/s/files/1/0230/4865/files/ecru-brayden-bottom-278649.jpg?v=1746041653"
  },
  {
    "product_id": 7893967208631,
    "product_title": "Aruba Brayden Bottom",
    "product_url": "https://midoribikinis.com/products/aruba-brayden-bottom",
    "image_url": "https://cdn.shopify.com/s/files/1/0230/4865/files/aruba-brayden-bottom-369850.jpg?v=1746040737"
  },
  {
    "product_id": 7893967208631,
    "product_title": "Aruba Brayden Bottom",
    "product_url": "https://midoribikinis.com/products/aruba-brayden-bottom",
    "image_url": "https://cdn.shopify.com/s/files/1/0230/4865/files/aruba-brayden-bottom-830943.jpg?v=1746040742"
  },
  {
    "product_id": 7318073999543,
    "product_title": "Aruba Cruz Bottom",
    "product_url": "https://midoribikinis.com/products/aruba-cruz-bottom",
    "image_url": "https://cdn.shopify.com/s/files/1/0230/4865/files/aruba-cruz-bottom-432978.jpg?v=1746041795"
  },
  {
    "product_id": 7318073999543,
    "product_title": "Aruba Cruz Bottom",
    "product_url": "https://midoribikinis.com/products/aruba-cruz-bottom",
    "image_url": "https://cdn.shopify.com/s/files/1/0230/4865/files/aruba-cruz-bottom-984744.jpg?v=1746041799"
  },
  {
    "product_id": 7893965799607,
    "product_title": "Ecru Cruz Bottom",
    "product_url": "https://midoribikinis.com/products/ecru-cruz-bottom",
    "image_url": "https://cdn.shopify.com/s/files/1/0230/4865/files/ecru-cruz-bottom-248454.jpg?v=1732486445"
  },
  {
    "product_id": 7893965799607,
    "product_title": "Ecru Cruz Bottom",
    "product_url": "https://midoribikinis.com/products/ecru-cruz-bottom",
    "image_url": "https://cdn.shopify.com/s/files/1/0230/4865/files/ecru-cruz-bottom-817333.jpg?v=1732486445"
  },
  {
    "product_id": 7829282586807,
    "product_title": "Matcha Kai Bottom",
    "product_url": "https://midoribikinis.com/products/matcha-kai-bottom",
    "image_url": "https://cdn.shopify.com/s/files/1/0230/4865/files/matcha-kai-bottom-898975.jpg?v=1746041299"
  },
  {
    "product_id": 7829282586807,
    "product_title": "Matcha Kai Bottom",
    "product_url": "https://midoribikinis.com/products/matcha-kai-bottom",
    "image_url": "https://cdn.shopify.com/s/files/1/0230/4865/files/matcha-kai-bottom-680046.jpg?v=1746041303"
  },
  {
    "product_id": 7829286453431,
    "product_title": "Drift Kai Bottom",
    "product_url": "https://midoribikinis.com/products/drift-kai-bottom",
    "image_url": "https://cdn.shopify.com/s/files/1/0230/4865/files/drift-kai-bottom-336872.jpg?v=1746041283"
  },
  {
    "product_id": 7829286453431,
    "product_title": "Drift Kai Bottom",
    "product_url": "https://midoribikinis.com/products/drift-kai-bottom",
    "image_url": "https://cdn.shopify.com/s/files/1/0230/4865/files/drift-kai-bottom-144440.jpg?v=1746041287"
  },
  {
    "product_id": 7829322760375,
    "product_title": "Canopy Tanner Bottom",
    "product_url": "https://midoribikinis.com/products/canopy-tanner-bottom",
    "image_url": "https://cdn.shopify.com/s/files/1/0230/4865/files/canopy-tanner-bottom-233149.jpg?v=1746041259"
  },
  {
    "product_id": 7829322760375,
    "product_title": "Canopy Tanner Bottom",
    "product_url": "https://midoribikinis.com/products/canopy-tanner-bottom",
    "image_url": "https://cdn.shopify.com/s/files/1/0230/4865/files/canopy-tanner-bottom-462742.jpg?v=1746041263"
  },
  {
    "product_id": 7784447541431,
    "product_title": "Peachy Brayden Bottom",
    "product_url": "https://midoribikinis.com/products/peachy-brayden-bottom",
    "image_url": "https://cdn.shopify.com/s/files/1/0230/4865/files/peachy-brayden-bottom-657668.jpg?v=1746041465"
  },
  {
    "product_id": 7784447541431,
    "product_title": "Peachy Brayden Bottom",
    "product_url": "https://midoribikinis.com/products/peachy-brayden-bottom",
    "image_url": "https://cdn.shopify.com/s/files/1/0230/4865/files/peachy-brayden-bottom-499870.jpg?v=1746041468"
  }
]